README.md
setup.py
posedion/__init__.py
posedion/poseidon.py
zzltest.egg-info/PKG-INFO
zzltest.egg-info/SOURCES.txt
zzltest.egg-info/dependency_links.txt
zzltest.egg-info/not-zip-safe
zzltest.egg-info/requires.txt
zzltest.egg-info/top_level.txt