Metadata-Version: 2.1
Name: zzltest
Version: 0.1.5
Summary: zzl test
Home-page: https://github.com/EnvisionIot
Author: Kid QU
Author-email: kidcrazequ@gmail.com
License: GPLv3
Platform: all
Classifier: Development Status :: 5 - Production/Stable
Classifier: Intended Audience :: Developers
Classifier: License :: OSI Approved :: GNU General Public License v3 (GPLv3)
Classifier: Programming Language :: Python
Classifier: Topic :: Software Development :: Libraries :: Python Modules
Classifier: Programming Language :: Python :: 3.6
